django_mem0_client-0.2.2.dist-info/licenses/LICENSE
mem0client/__init__.py
mem0client/admin.py
mem0client/apps.py
mem0client/memory_client.py
mem0client/memory_manager.py
mem0client/models.py
mem0client/tests.py
mem0client/views.py
mem0client/migrations/0001_initial.py
mem0client/migrations/0002_rename_action_memoryhistory_event_and_more.py
mem0client/migrations/__init__.py
django_mem0_client-0.2.2.dist-info/METADATA
django_mem0_client-0.2.2.dist-info/WHEEL
django_mem0_client-0.2.2.dist-info/top_level.txt
django_mem0_client-0.2.2.dist-info/RECORD
