Metadata-Version: 2.4
Name: django-mem0-client
Version: 0.2.2
Summary: A Django implementation of the mem0 memory system
Home-page: https://github.com/xjodoin/django-mem0-client
Author: Xavier Jodoin
Author-email: xavier@jodoin.me
Keywords: django,mem0,memory,ai
Classifier: Development Status :: 4 - Beta
Classifier: Framework :: Django
Classifier: Framework :: Django :: 4.0
Classifier: Intended Audience :: Developers
Classifier: License :: OSI Approved :: MIT License
Classifier: Programming Language :: Python :: 3
Classifier: Programming Language :: Python :: 3.8
Classifier: Programming Language :: Python :: 3.9
Classifier: Programming Language :: Python :: 3.10
Classifier: Topic :: Software Development :: Libraries :: Python Modules
Requires-Python: >=3.8
License-File: LICENSE
Requires-Dist: Django>=4.0.0
Requires-Dist: mem0ai>=0.1.102
Requires-Dist: pytz>=2022.1
Requires-Dist: pydantic>=1.9.0
Dynamic: author
Dynamic: author-email
Dynamic: classifier
Dynamic: description
Dynamic: description-content-type
Dynamic: home-page
Dynamic: keywords
Dynamic: license-file
Dynamic: requires-dist
Dynamic: requires-python
Dynamic: summary
